evaldocsloader/__init__.py
evaldocsloader/plugin.py
evaldocsloader-0.1.6.dist-info/LICENSE
evaldocsloader-0.1.6.dist-info/METADATA
evaldocsloader-0.1.6.dist-info/WHEEL
evaldocsloader-0.1.6.dist-info/entry_points.txt
evaldocsloader-0.1.6.dist-info/top_level.txt
evaldocsloader-0.1.6.dist-info/RECORD
