Metadata-Version: 2.1
Name: evaldocsloader
Version: 0.1.6
Summary: Mkdocs plugin for fetching additional .md files based on a fetched list, specifically designed to work with the LambdaFeedback architecture.
Author: Pierre Tharreau
License: MIT
License-File: LICENSE
Requires-Dist: mkdocs
Requires-Dist: requests
